{
  "caption": "Buffs",
  "creator": "Drevarr@github.com",
  "tags": "202506262310",
  "text": "<<tabs '[[202506262310-Boons]] [[202506262310-Stacking-Buffs]] [[202506262310-Personal-Buffs]] [[202506262310-Offensive-Buffs]] [[202506262310-Support-Buffs]] [[202506262310-Defensive-Buffs]] [[202506262310-Gear-Buff-Uptimes]] [[202506262310-Gear-Skill-Damage]][[202506262310-Conditions-In]] [[202506262310-Debuffs-In]] [[202506262310-Conditions-Out]] [[202506262310-Debuffs-Out]]' '202506262310-Boons' '$:/temp/tab1'>>",
  "title": "202506262310-Buffs"
}