{
  "title": "202503232332_fury_ChartData",
  "created": "20250323233208000",
  "creator": "Drevarr",
  "tags": "ChartData",
  "type": "text/vnd.tiddlywiki",
  "text": "\r\nconst names = [\"Tia Melusine\", \"Havocus Imperator\", \"Veil B\\u00f4t\", \"Niffuries\", \"King Modus\", \"Uncle Donk\", \"T A R Ancalim\\u00eb\", \"B\\u00e4sk\\u00e9t\", \"Flawed Jin\", \"Psyche V\", \"Havocus Imperator\", \"Muted Girl\", \"Iobtesr\", \"Rainy Twilight\", \"Tingelings\", \"Onysc\", \"Astro Bear\", \"Persueas\", \"Peewee Stability\", \"Time Turned Fragile\", \"Illusionary Oinkies\", \"Zyn Wintergreen Six\", \"Paralda\", \"O Divino\", \"Minnie Mew\", \"Orion Of The Hunt\", \"Ninja Tortoise\", \"Hephyt Wolf\"];\r\nconst professions = [\"Tempest\", \"Dragonhunter\", \"Chronomancer\", \"Firebrand\", \"Firebrand\", \"Dragonhunter\", \"Dragonhunter\", \"Holosmith\", \"Firebrand\", \"Chronomancer\", \"Firebrand\", \"Chronomancer\", \"Chronomancer\", \"Holosmith\", \"Chronomancer\", \"Spellbreaker\", \"Holosmith\", \"Spellbreaker\", \"Firebrand\", \"Chronomancer\", \"Chronomancer\", \"Firebrand\", \"Firebrand\", \"Warrior\", \"Druid\", \"Druid\", \"Druid\", \"Druid\"];\r\nconst ProfessionColor = {\"Warrior\": \"#FF9933\", \"Berserker\": \"#FFA750\", \"Spellbreaker\": \"#FFB66D\", \"Bladesworn\": \"#FFC48A\", \"Guardian\": \"#3399cc\", \"Dragonhunter\": \"#50A7D3\", \"Firebrand\": \"#6DB6DA\", \"Willbender\": \"#8AC4E1\", \"Revenant\": \"#CC6342\", \"Herald\": \"#D3795D\", \"Renegade\": \"#DA8F78\", \"Vindicator\": \"#E1A593\", \"Engineer\": \"#996633\", \"Scrapper\": \"#A77B50\", \"Holosmith\": \"#B6916D\", \"Mechanist\": \"#C4A78A\", \"Ranger\": \"#66CC33\", \"Druid\": \"#7BD350\", \"Soulbeast\": \"#91DA6D\", \"Untamed\": \"#A7E18A\", \"Thief\": \"#CC6666\", \"Daredevil\": \"#D37B7B\", \"Deadeye\": \"#DA9191\", \"Specter\": \"#E1A7A7\", \"Elementalist\": \"#EC5752\", \"Tempest\": \"#EE6F6A\", \"Weaver\": \"#F18783\", \"Catalyst\": \"#F49F9C\", \"Mesmer\": \"#993399\", \"Chronomancer\": \"#A750A7\", \"Mirage\": \"#B66DB6\", \"Virtuoso\": \"#C48AC4\", \"Necromancer\": \"#339966\", \"Reaper\": \"#50A77B\", \"Scourge\": \"#6DB691\", \"Harbinger\": \"#8AC4A7\"};\r\nconst short_Prof = {\"Guardian\": \"Gdn\", \"Dragonhunter\": \"Dgh\",\t\"Firebrand\": \"Fbd\",\t\"Willbender\": \"Wbd\", \"Warrior\": \"War\", \"Berserker\": \"Brs\", \"Spellbreaker\": \"Spb\", \"Bladesworn\": \"Bds\", \"Engineer\": \"Eng\", \"Scrapper\": \"Scr\", \"Holosmith\": \"Hls\", \"Mechanist\": \"Mec\", \"Ranger\": \"Rgr\", \"Druid\": \"Dru\", \"Soulbeast\": \"Slb\", \"Untamed\": \"Unt\", \"Thief\": \"Thf\", \"Daredevil\": \"Dar\", \"Deadeye\": \"Ded\", \"Specter\": \"Spe\", \"Elementalist\": \"Ele\", \"Tempest\": \"Tmp\", \"Weaver\": \"Wea\", \"Catalyst\": \"Cat\", \"Mesmer\": \"Mes\", \"Chronomancer\": \"Chr\", \"Mirage\": \"Mir\", \"Virtuoso\": \"Vir\", \"Necromancer\": \"Nec\", \"Reaper\": \"Rea\", \"Scourge\": \"Scg\", \"Harbinger\": \"Har\", \"Revenant\": \"Rev\", \"Herald\": \"Her\", \"Renegade\": \"Ren\", \"Vindicator\": \"Vin\", \"Unknown\": \"Ukn\"};\r\noption = {\r\n  title: [\r\n    {text: 'Fury per Fight for all Fights Present', left: 'center'},\r\n    {text: 'Output in seconds across all fights \\nupper: Q3 + 1.5 * IQR \\nlower: Q1 - 1.5 * IQR', borderColor: '#999', borderWidth: 1, textStyle: {fontSize: 10}, left: '1%', top: '90%'}\r\n  ],\r\ndataset: [\r\n    {\r\n      // prettier-ignore\r\n      source: \r\n[[0.0, 24.232, 0.0, 0.0, 0.0, 117.6077, 0.0, 0.0, 45.1496, 5.2377, 166.8686, 0.0, 55.0971, 0.0, 23.598, 0.0, 0.0, 0.0, 0.0, 49.938, 0.0], [6.6066, 0.0, 5.2718, 15.3595, 48.9974, 24.3964, 34.4833, 23.8549, 31.6692, 11.0888, 9.1908, 41.6532, 42.6, 143.869, 63.104], [0.0, 0.0, 0.0, 0.0, 22.5036, 20.9824, 68.2272, 109.2624, 142.852, 48.1545, 197.744], [0.0, 42.9527, 54.1995, 0.0, 0.0, 159.0413, 0.0, 0.0, 44.845, 38.2109, 52.8494, 0.0, 7.2883, 0.0, 31.5324, 32.8016, 23.5704, 71.3172, 26.128, 159.0288, 50.048], [111.3177, 69.8746, 0.0, 0.0, 0.0, 337.0464, 211.9689, 0.0, 0.0, 0.0, 0.0, 0.0, 0.0, 0.0, 0.0, 0.0, 0.0, 0.0, 0.0, 0.0, 176.528], [0.0, 0.0, 10.79, 0.0, 40.0624, 68.6842, 7.2072, 0.0, 59.8637, 26.4316, 104.7744, 6.4615, 57.0007, 30.9837, 0.0, 44.156, 35.1072, 0.0, 170.968, 203.0218, 68.816], [19.3596, 5.9705, 129.5597, 17.9322, 0.0, 12.0899, 18.0778, 57.78, 72.1951, 40.5206, 17.4283, 60.6024, 89.7728, 59.8644, 79.4748, 119.706, 329.6502, 165.104], [111.6848, 77.2248, 175.1412, 55.664, 767.7968, 133.552], [11.388, 12.5534, 75.7796, 0.0, 0.0, 27.0851, 123.1191, 149.7658, 0.0, 0.0, 10.9379, 19.0836, 49.9992, 43.194, 55.1256, 143.278, 412.8802, 317.152], [84.8232, 0.0, 98.2901, 164.1408, 1.9305, 0.0, 20.923, 3.1603, 57.0096, 0.0, 0.0, 32.4094, 47.2644, 59.6936, 38.916, 78.7332, 213.71, 467.5743, 168.096], [0.0, 71.2962, 512.2448, 52.7985, 206.7878, 1058.6285], [19.967, 72.0179, 191.9125, 0.0, 83.692, 240.6336, 70.1844, 0.0, 49.9996, 31.5146, 166.5605, 0.0, 100.2408, 38.8573, 93.1608, 53.0536, 22.3284, 77.1264, 97.554, 343.621, 183.872], [19.8666, 344.855, 97.8549, 0.0, 54.8496, 106.8314, 90.2909, 36.9881, 53.7373, 69.6707, 178.0452, 62.5488, 49.4592, 233.4804, 199.652, 476.789], [3.984, 39.468, 0.0, 54.6153, 48.0896, 198.7632, 118.9997, 25.3457, 34.3885, 111.3552, 96.0808, 86.9952, 158.5788, 328.73, 599.256, 376.72], [118.7957, 72.4022, 300.1784, 69.7984, 181.8072, 129.7456, 55.7244, 438.2856, 282.438, 663.462, 443.36], [51.5307, 7.5014, 101.5384, 26.6017, 55.6209, 311.7082, 104.5044, 5.2569, 110.5662, 132.6884, 350.9942, 175.7451, 20.1787, 31.3454, 109.9188, 246.1448, 220.0548, 492.7932, 228.194, 0.0, 0.0], [0.0, 63.0731, 67.2349, 0.0, 71.9751, 179.7581, 47.8335, 0.0, 61.7849, 66.8746, 312.9365, 137.8043, 66.9541, 60.499, 67.374, 111.0872, 23.9016, 164.6352, 404.984, 605.201, 405.824], [25.3573, 0.0, 144.636, 13.8105, 36.9891, 297.8438, 88.7172, 0.0, 103.8183, 110.0138, 622.175, 136.6032, 0.0, 0.0, 6.3612, 178.4168, 35.6316, 218.154, 319.784, 647.7077, 430.032], [0.0, 0.0, 194.4856, 81.7512, 371.7888, 525.4, 1447.3102, 935.68], [66.7906, 42.0341, 96.8606, 0.0, 36.0836, 327.9629, 79.6653, 0.0, 113.4715, 53.3715, 161.1677, 113.4494, 71.3053, 98.9946, 77.7708, 124.2344, 65.2464, 191.7036, 465.334, 714.2917, 835.04], [392.663, 58.1295, 0.0, 84.5589, 88.8641, 376.7256, 140.2067, 155.773, 112.2307, 289.0584, 101.924, 83.9316, 282.3024, 382.122, 818.9237, 508.64], [0.0, 0.0, 78.5374, 74.0792, 315.864, 71.988, 191.9423, 67.713, 228.2508, 217.3272, 75.2928, 565.3464, 459.37, 1009.1637, 726.784], [0.0, 0.0, 0.0, 0.0, 0.0, 263.2627, 70.6134, 0.0, 94.3526, 34.2108, 253.3075, 82.5915, 114.7629, 21.0885, 214.776, 194.22, 138.2208, 329.8884, 495.296, 1125.0912, 842.656], [0.0, 286.5278, 21.1208, 183.9303, 581.3453, 87.4302, 0.0, 153.8882, 103.7374, 439.7443, 109.6387, 78.8111, 77.1613, 230.3712, 233.7944, 106.6464, 348.552, 321.204, 642.6545, 540.736], [46.9375, 73.0677, 200.1453, 0.0, 130.0382, 643.4957, 87.516, 38.4971, 68.3922, 36.907, 584.5795, 190.4492, 287.288, 67.5002, 223.9416, 0.0, 0.0, 0.0, 551.386, 814.465, 907.936], [24.4462, 140.4054, 276.3615, 20.412, 134.2639, 738.3149, 164.4357, 47.3834, 99.9758, 12.9285, 708.6139, 261.3602, 227.4046, 102.2078, 224.2152, 219.1864, 98.0076, 372.036, 591.714, 892.6418, 1083.104], [94.8431, 71.2525, 405.3426, 57.7462, 126.4161, 790.1069, 185.8857, 21.1108, 84.676, 72.1565, 664.2389, 213.1887, 368.7098, 75.7568, 314.0244, 145.8144, 114.8712, 667.44, 715.68, 1357.838, 1219.92], [118.2644, 0.0, 385.1971, 62.5455, 208.9282, 837.9149, 218.7042, 26.7835, 106.2082, 20.8182, 954.5256, 223.668, 331.1807, 115.1461, 335.502, 307.8304, 125.9112, 794.13, 721.218, 1439.2845, 1315.392]]\r\n    },\r\n\t{\r\n\t  transform: {\r\n\t\ttype: 'boxplot',\r\n\t\tconfig: {\r\n\t\t  itemNameFormatter: function (params) {\r\n\t\t\treturn names[params.value]+\" (\"+short_Prof[professions[params.value]]+\")\";\r\n\t\t  }\r\n\t\t}\r\n\t  },\r\n\t},\r\n\t{\r\n\t  fromDatasetIndex: 1,\r\n\t  fromTransformResult: 1\r\n\t}\r\n  ],\r\n  dataZoom: [{type: 'slider', show: true, yAxisIndex: [0], start: 100, end: 50 },{type: 'inside', yAxisIndex: [0], start: 100, end: 50 },],\r\n  tooltip: {trigger: 'item'},\r\n  grid: {left: '25%', right: '10%', bottom: '15%'},\r\n  yAxis: {type: 'category', boundaryGap: true, nameGap: 30, splitArea: {show: true}, splitLine: {show: true}},\r\n  xAxis: {type: 'value', name: 'Sec', splitArea: {show: true}},\r\n  series: [\r\n\t{\r\n\t  name: 'boxplot',\r\n\t  type: 'boxplot',\r\n\t  datasetIndex: 1,\r\n\t  tooltip: {trigger: 'item',\r\n\t\t  formatter: function (params) {\r\n\t\t\t//console.log(params.value);\r\n\t\t  return `<u><b>${params.value[0]}</b></u>\r\n\t<table>\r\n\t  <tr>\r\n\t\t  <td align=\"right\">&#x2022;</td>\r\n\t\t<td align=\"left\">Low   :</td>\r\n\t\t<td style=\"color:blue;\"align=\"right\"><b>${params.value[1].toFixed(2)}</b></td>\r\n\t  </tr>\r\n\t  <tr>\r\n\t\t  <td align=\"right\">&#x2022;</td>\r\n\t\t<td align=\"left\">Q1    :</td>\r\n\t\t<td style=\"color:blue;\"align=\"right\"><b>${params.value[2].toFixed(2)}</b></td>\r\n\t  </tr>\r\n\t  <tr>\r\n\t\t  <td align=\"right\">&#x2022;</td>\r\n\t\t<td align=\"left\">Q2    :</td>\r\n\t\t<td style=\"color:blue;\"align=\"right\"><b>${params.value[3].toFixed(2)}</b></td>\r\n\t  </tr>\r\n\t  <tr>\r\n\t\t  <td align=\"right\">&#x2022;</td>\r\n\t\t<td align=\"left\">Q3    :</td>\r\n\t\t<td style=\"color:blue;\"align=\"right\"><b>${params.value[4].toFixed(2)}</b></td>\r\n\t  </tr>\r\n\t  <tr>\r\n\t\t  <td align=\"right\">&#x2022;</td>\r\n\t\t<td align=\"left\">High  :</td>\r\n\t\t<td style=\"color:blue;\"align=\"right\"><b>${params.value[5].toFixed(2)}</b></td>\r\n\t  </tr>  \r\n\t</table>`;              \r\n\t\t},    \r\n\t\taxisPointer: {type: 'shadow'}},      \r\n\t  itemStyle: {\r\n\t\tborderColor: function (seriesIndex) {\r\n\t\t  let myIndex = names.indexOf(seriesIndex.name.split(\" (\")[0]);\r\n\t\t  return ProfessionColor[professions[myIndex]];\r\n\t\t\t\t},\r\n\t\tborderWidth: 2\r\n\t  },\r\n\t  encode:{tooltip: [ 1, 2, 3, 4, 5]},\r\n\t  },\r\n\t{\r\n\t  name: 'outlier',\r\n\t  type: 'scatter',\r\n\t  encode: { x: 1, y: 0 },\r\n\t  datasetIndex: 2,\r\n\t}\r\n  ]\r\n};\n\n"
}